Refrapt-0.4.10.data/data/refrapt/refrapt.conf.example
refrapt/__init__.py
refrapt/classes.py
refrapt/helpers.py
refrapt/refrapt.py
refrapt/settings.py
Refrapt-0.4.10.dist-info/LICENSE
Refrapt-0.4.10.dist-info/METADATA
Refrapt-0.4.10.dist-info/WHEEL
Refrapt-0.4.10.dist-info/entry_points.txt
Refrapt-0.4.10.dist-info/top_level.txt
Refrapt-0.4.10.dist-info/RECORD
