Metadata-Version: 2.1
Name: Refrapt
Version: 0.4.10
Summary: A tool to mirror Debian repositories for use as a local mirror.
Home-page: https://github.com/Progeny42/Refrapt
Author: Progeny42
Keywords: Mirror,Debian,Repository
Classifier: Development Status :: 4 - Beta
Classifier: Intended Audience :: Developers
Classifier: Intended Audience :: End Users/Desktop
Classifier: Intended Audience :: System Administrators
Classifier: Natural Language :: English
Classifier: Operating System :: Microsoft :: Windows :: Windows 10
Classifier: Operating System :: POSIX :: Linux
Classifier: Programming Language :: Python :: 3.9
Classifier: Programming Language :: Python :: Implementation
Classifier: Topic :: System :: Archiving :: Mirroring
Requires-Python: >=3.9
License-File: LICENSE
Requires-Dist: Click >=7.1.2
Requires-Dist: Colorama >=0.4.4
Requires-Dist: tqdm >=4.60.0
Requires-Dist: wget >=3.2
Requires-Dist: filelock ==3.0.12
Requires-Dist: tendo ==0.2.15
